equi7grid/__init__.py
equi7grid/copernicusgrid.py
equi7grid/equi7_to_lonlat.py
equi7grid/equi7grid.py
equi7grid/image2equi7grid.py
equi7grid/data/__init__.py
equi7grid/data/create_distortion_files.py
equi7grid/data/equi7grid.dat
equi7grid/data/make_equi7data.py
equi7grid/grids/AF/GEOG/EQUI7_V14_AF_GEOG_LAND.dbf
equi7grid/grids/AF/GEOG/EQUI7_V14_AF_GEOG_LAND.prj
equi7grid/grids/AF/GEOG/EQUI7_V14_AF_GEOG_LAND.shp
equi7grid/grids/AF/GEOG/EQUI7_V14_AF_GEOG_LAND.shx
equi7grid/grids/AF/GEOG/EQUI7_V14_AF_GEOG_TILE_T1.dbf
equi7grid/grids/AF/GEOG/EQUI7_V14_AF_GEOG_TILE_T1.prj
equi7grid/grids/AF/GEOG/EQUI7_V14_AF_GEOG_TILE_T1.shp
equi7grid/grids/AF/GEOG/EQUI7_V14_AF_GEOG_TILE_T1.shx
equi7grid/grids/AF/GEOG/EQUI7_V14_AF_GEOG_TILE_T3.dbf
equi7grid/grids/AF/GEOG/EQUI7_V14_AF_GEOG_TILE_T3.prj
equi7grid/grids/AF/GEOG/EQUI7_V14_AF_GEOG_TILE_T3.shp
equi7grid/grids/AF/GEOG/EQUI7_V14_AF_GEOG_TILE_T3.shx
equi7grid/grids/AF/GEOG/EQUI7_V14_AF_GEOG_TILE_T6.dbf
equi7grid/grids/AF/GEOG/EQUI7_V14_AF_GEOG_TILE_T6.prj
equi7grid/grids/AF/GEOG/EQUI7_V14_AF_GEOG_TILE_T6.shp
equi7grid/grids/AF/GEOG/EQUI7_V14_AF_GEOG_TILE_T6.shx
equi7grid/grids/AF/GEOG/EQUI7_V14_AF_GEOG_ZONE.dbf
equi7grid/grids/AF/GEOG/EQUI7_V14_AF_GEOG_ZONE.prj
equi7grid/grids/AF/GEOG/EQUI7_V14_AF_GEOG_ZONE.shp
equi7grid/grids/AF/GEOG/EQUI7_V14_AF_GEOG_ZONE.shx
equi7grid/grids/AF/PROJ/EQUI7_V14_AF_PROJ_LAND.dbf
equi7grid/grids/AF/PROJ/EQUI7_V14_AF_PROJ_LAND.prj
equi7grid/grids/AF/PROJ/EQUI7_V14_AF_PROJ_LAND.shp
equi7grid/grids/AF/PROJ/EQUI7_V14_AF_PROJ_LAND.shx
equi7grid/grids/AF/PROJ/EQUI7_V14_AF_PROJ_TILE_T1.dbf
equi7grid/grids/AF/PROJ/EQUI7_V14_AF_PROJ_TILE_T1.prj
equi7grid/grids/AF/PROJ/EQUI7_V14_AF_PROJ_TILE_T1.shp
equi7grid/grids/AF/PROJ/EQUI7_V14_AF_PROJ_TILE_T1.shx
equi7grid/grids/AF/PROJ/EQUI7_V14_AF_PROJ_TILE_T3.dbf
equi7grid/grids/AF/PROJ/EQUI7_V14_AF_PROJ_TILE_T3.prj
equi7grid/grids/AF/PROJ/EQUI7_V14_AF_PROJ_TILE_T3.shp
equi7grid/grids/AF/PROJ/EQUI7_V14_AF_PROJ_TILE_T3.shx
equi7grid-0.2.6.dist-info/licenses/LICENSE.txt
equi7grid-0.2.6.dist-info/METADATA
equi7grid-0.2.6.dist-info/WHEEL
equi7grid-0.2.6.dist-info/top_level.txt
equi7grid-0.2.6.dist-info/RECORD
