Metadata-Version: 2.4
Name: Equi7Grid
Version: 0.2.6
Summary: Definition and tools for Equi7Grid and its tiling system
Home-page: https://github.com/pyscaffold/pyscaffold/
Author: TU Wien
Author-email: remote.sensing@geo.tuwien.ac.at
License: MIT
Project-URL: Documentation, https://equi7grid.readthedocs.io/
Platform: any
Classifier: Development Status :: 4 - Beta
Classifier: Programming Language :: Python
License-File: LICENSE.txt
Requires-Dist: importlib-metadata; python_version < "3.8"
Requires-Dist: numpy
Requires-Dist: scipy
Requires-Dist: veranda
Requires-Dist: pytileproj
Requires-Dist: geographiclib
Requires-Dist: geopathfinder
Provides-Extra: testing
Requires-Dist: setuptools; extra == "testing"
Requires-Dist: pytest; extra == "testing"
Requires-Dist: pytest-cov; extra == "testing"
Requires-Dist: approvaltests; extra == "testing"
Dynamic: license-file
